{"current_name": 8, "shield": {"stability": 3, "cost": 0, "triggers": {"enter": [{"actions": [{"action": "protect", "target": "team", "amount": 1}]}], "timer": [{"goal": 10, "progress": 0, "actions": [{"action": "finish", "target": "self"}]}], "exit": [{"actions": [{"action": "protect", "target": "team", "amount": -1}]}]}}, "bomb": {"stability": 3, "cost": 10, "triggers": {"timer": [{"goal": 12, "progress": 0, "actions": [{"action": "damage", "target": "enemy_team", "amount": 3}, {"action": "finish", "target": "self"}]}]}}, "attack": {"stability": 3, "cost": 4, "triggers": {"timer": [{"goal": 2, "progress": 0, "actions": [{"action": "destabilize", "target": "across", "amount": 1}]}, {"goal": 10, "progress": 0, "actions": [{"action": "finish", "target": "self"}]}]}}, "1": {"stability": 8, "cost": 8, "triggers": {}}, "2": {"stability": 2, "cost": 4, "triggers": {}}, "3": {"stability": 5, "cost": 9, "triggers": {}}, "4": {"stability": 9, "cost": 3, "triggers": {}}, "5": {"stability": 3, "cost": 4, "triggers": {}}, "6": {"stability": 6, "cost": 3, "triggers": {}}, "7": {"stability": 2, "cost": 3, "triggers": {}}, "8": {"stability": 5, "cost": 1, "triggers": {}}}